Metadata-Version: 2.1
Name: classattr
Version: 1.0.5
Summary: classattr provides tools to manage class and object attributes
Home-page: https://framagit.org/makeforartandscience/classattr
Author: Thierry Dassé
License: MIT License
Platform: UNKNOWN
Classifier: Programming Language :: Python :: 3
Classifier: Operating System :: OS Independent
License-File: LICENSE
